test/__init__.py
test/test_config.py
test/test_main.py
vault_printer/__init__.py
vault_printer/config.py
vault_printer/entities.py
vault_printer/main.py
vault_printer-0.3.1.dist-info/LICENSE.md
vault_printer-0.3.1.dist-info/METADATA
vault_printer-0.3.1.dist-info/WHEEL
vault_printer-0.3.1.dist-info/entry_points.txt
vault_printer-0.3.1.dist-info/top_level.txt
vault_printer-0.3.1.dist-info/RECORD
