Metadata-Version: 2.1
Name: vault-printer
Version: 0.3.1
Summary: A program to get all secrets from a vault servers kv_store for printing
Home-page: https://github.com/DerMolly/vault_printer
Author: Philip Molares
Author-email: philipmolares@yahoo.de
License: MIT
Platform: UNKNOWN
Classifier: Programming Language :: Python :: 3.7
Classifier: License :: OSI Approved :: MIT License
Classifier: Operating System :: OS Independent
Requires-Python: >=3.7
Requires-Dist: hvac
Requires-Dist: hvac[parser]
Requires-Dist: jinja2
